opengrammar/__init__.py
opengrammar-0.1.0a0.dist-info/LICENSE
opengrammar-0.1.0a0.dist-info/METADATA
opengrammar-0.1.0a0.dist-info/WHEEL
opengrammar-0.1.0a0.dist-info/top_level.txt
opengrammar-0.1.0a0.dist-info/RECORD
